CARMA/Makefile
CARMA/make-carma-human.csh
CARMA/make-carma.csh
CARMA/source/base/.git
CARMA/source/base/Makefile
CARMA/source/base/actdropl.F90
CARMA/source/base/bhmie.F90
CARMA/source/base/calcrs.F90
CARMA/source/base/carma_condensate_mod.F90
CARMA/source/base/carma_constants_mod.F90
CARMA/source/base/carma_enums_mod.F90
CARMA/source/base/carma_globaer.h
CARMA/source/base/carma_mod.F90
CARMA/source/base/carma_planet_mod.F90
CARMA/source/base/carma_precision_mod.F90
CARMA/source/base/carma_types_mod.F90
CARMA/source/base/carmaelement_mod.F90
CARMA/source/base/carmagas_mod.F90
CARMA/source/base/carmagroup_mod.F90
CARMA/source/base/carmasolute_mod.F90
CARMA/source/base/carmastate_mod.F90
CARMA/source/base/coagl.F90
CARMA/source/base/coagp.F90
CARMA/source/base/csolve.F90
CARMA/source/base/detrain.F90
CARMA/source/base/downgevapply.F90
CARMA/source/base/downgxfer.F90
CARMA/source/base/evap_ingrp.F90
CARMA/source/base/evap_mono.F90
CARMA/source/base/evap_poly.F90
CARMA/source/base/evapp.F90
CARMA/source/base/freezaerl_koop2000.F90
CARMA/source/base/freezaerl_mohler2010.F90
CARMA/source/base/freezaerl_tabazadeh2000.F90
CARMA/source/base/freezdropl.F90
CARMA/source/base/freezglaerl_murray2010.F90
CARMA/source/base/gasexchange.F90
CARMA/source/base/growevapl.F90
CARMA/source/base/growp.F90
CARMA/source/base/gsolve.F90
CARMA/source/base/hetnucl.F90
CARMA/source/base/homnucgen.F90
CARMA/source/base/maxconc.F90
CARMA/source/base/melticel.F90
CARMA/source/base/microfast.F90
CARMA/source/base/microslow.F90
CARMA/source/base/mie.F90
CARMA/source/base/miess.F90
CARMA/source/base/newstate.F90
CARMA/source/base/nsubsteps.F90
CARMA/source/base/pheat.F90
CARMA/source/base/planck.F90
CARMA/source/base/prestep.F90
CARMA/source/base/psolve.F90
CARMA/source/base/rhoice_heymsfield2010.F90
CARMA/source/base/rhopart.F90
CARMA/source/base/setupatm.F90
CARMA/source/base/setupbdif.F90
CARMA/source/base/setupbins.F90
carmapy-0.5.13.dist-info/METADATA
carmapy-0.5.13.dist-info/WHEEL
carmapy-0.5.13.dist-info/top_level.txt
carmapy-0.5.13.dist-info/RECORD
carmapy-0.5.13.dist-info/licenses/LICENSE
