Metadata-Version: 2.4
Name: carmapy
Version: 0.5.13
Summary: A python wrapper of the CARMA cloud aerosol model
Author-email: Wolf Cukier <wcukier@uchicago.edu>
License-File: LICENSE
Requires-Dist: requests
Requires-Dist: importlib-metadata; python_version < "3.10"
Requires-Dist: matplotlib
Requires-Dist: numpy
Requires-Dist: scipy
Requires-Dist: pyfastchem
Requires-Dist: f90nml
Dynamic: license-file
